evolufy/__init__.py
evolufy/agents.py
evolufy/brokers.py
evolufy/data_sources.py
evolufy/information.py
evolufy/investment_strategy.py
evolufy/skeleton.py
evolufy/.ipynb_checkpoints/agents-checkpoint.py
evolufy/.ipynb_checkpoints/brokers-checkpoint.py
evolufy/.ipynb_checkpoints/data_sources-checkpoint.py
evolufy/.ipynb_checkpoints/information-checkpoint.py
evolufy/.ipynb_checkpoints/investment_strategy-checkpoint.py
evolufy/.ipynb_checkpoints/modern_portfolio_theory-checkpoint.py
evolufy/.ipynb_checkpoints/skeleton-checkpoint.py
evolufy-1.0.6.dist-info/LICENSE.txt
evolufy-1.0.6.dist-info/METADATA
evolufy-1.0.6.dist-info/WHEEL
evolufy-1.0.6.dist-info/top_level.txt
evolufy-1.0.6.dist-info/RECORD
