Metadata-Version: 2.1
Name: evolufy
Version: 1.0.6
Summary: Investment Portfolio Optimization Library
Home-page: https://github.com/sanchezcarlosjr/evolufy
Author: sanchezcarlosjr
Author-email: 24639141+sanchezcarlosjr@users.noreply.github.com
License: MIT
Project-URL: Documentation, https://carlos-eduardo-sanchez-torres.sanchezcarlosjr.com/Evolufy-A-Browser-based-Investment-Portfolio-Optimization-Library-Utilizing-Genetic-Algorithms-and--c3a1983ae6d24851b979d114b3784c2d
Platform: any
Classifier: Development Status :: 4 - Beta
Classifier: Programming Language :: Python
License-File: LICENSE.txt
Requires-Dist: injector ==0.21.0
Requires-Dist: dacite >=1.8.1
Requires-Dist: numpy
Requires-Dist: cvxopt ==1.3.2
Requires-Dist: darts
Provides-Extra: testing
Requires-Dist: setuptools ; extra == 'testing'
Requires-Dist: pytest ; extra == 'testing'
Requires-Dist: pytest-asyncio ; extra == 'testing'
Requires-Dist: pytest-cov ; extra == 'testing'
